epi/__init__.py
epi/macro.py
epimodel/__init__.py
epimodel/macro.py
epimodels/__init__.py
epimodels/macro.py
tests/__init__.py
tests/test.py
ziggie/__init__.py
ziggie/macro.py
ziggie/samples.py
ziggie/tests/__init__.py
ziggie/tests/test.py
ziggy/__init__.py
ziggy/macro.py
ziggie-0.1.1.dist-info/LICENSE.txt
ziggie-0.1.1.dist-info/METADATA
ziggie-0.1.1.dist-info/WHEEL
ziggie-0.1.1.dist-info/top_level.txt
ziggie-0.1.1.dist-info/RECORD
